CHANGELOG.rst
LICENSE
MANIFEST.in
Makefile
README.rst
setup.py
tox.ini
django_openS3/__init__.py
django_openS3/constants.py
django_openS3/storage.py
django_openS3/test_settings.py
django_openS3.egg-info/PKG-INFO
django_openS3.egg-info/SOURCES.txt
django_openS3.egg-info/dependency_links.txt
django_openS3.egg-info/requires.txt
django_openS3.egg-info/top_level.txt
docs/Makefile
docs/changelog.rst
docs/conf.py
docs/index.rst
docs/storage.rst
docs/_build/.buildinfo
docs/_build/changelog.html
docs/_build/genindex.html
docs/_build/index.html
docs/_build/objects.inv
docs/_build/py-modindex.html
docs/_build/search.html
docs/_build/searchindex.js
docs/_build/storage.html
docs/_build/.doctrees/changelog.doctree
docs/_build/.doctrees/environment.pickle
docs/_build/.doctrees/index.doctree
docs/_build/.doctrees/storage.doctree
docs/_build/_modules/index.html
docs/_build/_modules/django_openS3/storage.html
docs/_build/_sources/changelog.txt
docs/_build/_sources/index.txt
docs/_build/_sources/storage.txt
docs/_build/_static/ajax-loader.gif
docs/_build/_static/basic.css
docs/_build/_static/comment-bright.png
docs/_build/_static/comment-close.png
docs/_build/_static/comment.png
docs/_build/_static/default.css
docs/_build/_static/doctools.js
docs/_build/_static/down-pressed.png
docs/_build/_static/down.png
docs/_build/_static/file.png
docs/_build/_static/jquery.js
docs/_build/_static/minus.png
docs/_build/_static/plus.png
docs/_build/_static/pygments.css
docs/_build/_static/searchtools.js
docs/_build/_static/sidebar.js
docs/_build/_static/underscore.js
docs/_build/_static/up-pressed.png
docs/_build/_static/up.png
docs/_build/_static/websupport.js