Metadata-Version: 1.1
Name: django-openS3
Version: 0.1.0
Summary: An openS3 wrapper for use with Django
Home-page: http://github.com/logston/django_openS3
Author: Paul Logston
Author-email: code@logston.me
License: The MIT License (MIT)
